{
    "1": {
        "steps": 9069,
        "pushups": 30,
        "hops": 60,
        "eating_window_min": 450,
        "lines_of_code": 0,
        "total_applications": 0,
        "total_media_min": 32,
        "cleaning_completed": true,
        "%_book_read": 0.06,
        "meaningful_gaming_min": 0
    },

    "2": {
        "steps": 10108,
        "pushups": 30,
        "hops": 60,
        "eating_window_min": 540,
        "lines_of_code": 0,
        "total_applications": 0,
        "total_media_min": 44,
        "cleaning_completed": true,
        "%_book_read": 0.16,
        "meaningful_gaming_min": 0
    },

    "3": {
        "steps": 9428,
        "pushups": 30,
        "hops": 60,
        "eating_window_min": 399,
        "lines_of_code": 0,
        "total_applications": 0,
        "total_media_min": 60,
        "cleaning_completed": true,
        "%_book_read": 0,
        "meaningful_gaming_min": 0
    }
}